bark/__init__.py
bark/core.so
bark/pip_package.py
bark/tests.py
bark/benchmark/__init__.py
bark/benchmark/benchmark_analyzer.py
bark/benchmark/benchmark_result.py
bark/benchmark/benchmark_runner.py
bark/benchmark/benchmark_runner_mp.py
bark/benchmark/benchmark_runner_mp_config.py
bark/benchmark/scenario_dumper.py
bark/benchmark/templates/template_traj.xml
bark/benchmark/tests/__init__.py
bark/benchmark/tests/py_benchmark_analyzer_tests.py
bark/benchmark/tests/py_benchmark_process_tests.py
bark/benchmark/tests/py_benchmark_result_tests.py
bark/benchmark/tests/py_benchmark_runner_tests.py
bark/benchmark/tests/py_scenario_dumper_tests.py
bark/benchmark/tests/test_evaluator.py
bark/examples/__init__.py
bark/examples/barkscape_example.py
bark/examples/benchmark_database.py
bark/examples/highway.py
bark/examples/highway_rss.py
bark/examples/highway_stochastic_intents.py
bark/examples/interaction_dataset.py
bark/examples/intersection.py
bark/examples/merging.py
bark/examples/merging_rss.py
bark/examples/parametric_observer.py
bark/examples/paths.py
bark/examples/params/highway_merge_configurable.json
bark/examples/params/interaction_example.json
bark/examples/params/interaction_merging_chn.json
bark/examples/params/interaction_merging_deu.json
bark/examples/params/interaction_merging_deu_withIDM.json
bark/examples/params/intersection_configurable.json
bark/examples/params/intersection_configurable2.json
bark/examples/params/uct_planner.json
bark/examples/scenarios/highway_merging_dump.bark_scenarios
bark/runtime/__init__.py
bark/runtime/runtime.py
bark/runtime/commons/__init__.py
bark/runtime/commons/commons.py
bark/runtime/commons/model_json_conversion.py
bark/runtime/commons/parameters.py
bark/runtime/commons/xodr_parser.py
bark/runtime/scenario/__init__.py
bark/runtime/scenario/scenario.py
bark/runtime/scenario/interaction_dataset_processing/__init__.py
bark/runtime/scenario/interaction_dataset_processing/agent_track_info.py
bark_simulator-1.4.10.dist-info/LICENSE
bark_simulator-1.4.10.dist-info/METADATA
bark_simulator-1.4.10.dist-info/WHEEL
bark_simulator-1.4.10.dist-info/top_level.txt
bark_simulator-1.4.10.dist-info/RECORD
