Metadata-Version: 2.1
Name: bark-simulator
Version: 1.4.10
Summary: A tool for Behavior benchmARKing
Home-page: https://github.com/bark-simulator/bark
Author: Julian Bernhard, Klemens Esterle, Patrick Hart, Tobias Kessler
Author-email: autonomous-driving@fortiss.org
License: MIT
Keywords: simulator autonomous driving machine learning
Platform: UNKNOWN
Classifier: Development Status :: 4 - Beta
Classifier: Intended Audience :: Science/Research
Classifier: License :: OSI Approved :: MIT License
Classifier: Operating System :: OS Independent
Classifier: Programming Language :: Python :: 3.7
Requires-Python: >=3.7
Requires-Dist: matplotlib (>=3.3.2)
Requires-Dist: numpy (>=1.18.1)
Requires-Dist: lxml (>=4.4.2)
Requires-Dist: scipy (>=1.4.1)
Requires-Dist: sphinx (>=2.3.1)
Requires-Dist: sphinx-rtd-theme (>=0.4.3)
Requires-Dist: pandas (>=0.24.2)
Requires-Dist: autopep8 (>=1.4.4)
Requires-Dist: cpplint (>=1.4.4)
Requires-Dist: pygame (>=1.9.6)
Requires-Dist: aabbtree (>=2.3.1)
Requires-Dist: ray (>=1.3.0)
Requires-Dist: psutil (>=5.7.2)
Requires-Dist: notebook (>=6.0.3)
Requires-Dist: jupyter (>=1.0.0)
Requires-Dist: ipython (>=7.13.0)
